{
  "description": "The Computer Security Incident Response Team (CSIRT) Services Framework is a high-level document describing in a structured way a collection of cyber security services and associated functions that Computer Security Incident Response Teams and other teams providing incident management related services may provide",
  "icon": "user",
  "name": "FIRST CSIRT Services Framework",
  "namespace": "first",
  "type": "first-csirt-services-framework",
  "uuid": "4a72488f-ef5b-4895-a5d9-c625dee663cb",
  "version": 1
}
